start_time_estimator/__init__.py
start_time_estimator/concurrency_oracle.py
start_time_estimator/config.py
start_time_estimator/estimator.py
start_time_estimator/resource_availability.py
start_time_estimator/utils.py
start_time_estimator-1.10.11.dist-info/LICENSE
start_time_estimator-1.10.11.dist-info/METADATA
start_time_estimator-1.10.11.dist-info/WHEEL
start_time_estimator-1.10.11.dist-info/RECORD
