Metadata-Version: 2.1
Name: start-time-estimator
Version: 1.10.11
Summary: Python package to estimate the enabled time, enabling activity, and resource availability time of each activity instance in an event log.
Author: David Chapela de la Campa
Author-email: david.chapela.delacampa@gmail.com
Requires-Python: >=3.9,<3.12
Classifier: Programming Language :: Python :: 3
Classifier: Programming Language :: Python :: 3.9
Classifier: Programming Language :: Python :: 3.10
Classifier: Programming Language :: Python :: 3.11
Requires-Dist: pandas (>=2.0,<3.0)
Requires-Dist: pix-framework (>=0.10.0,<0.11.0)
